config_manager/__init__.py
config_manager/config.py
config_manager/exceptions.py
config_manager/typing.py
config_manager/providers/__init__.py
config_manager/providers/base.py
config_manager/providers/composite.py
config_manager/providers/env.py
config_manager/providers/factory.py
config_manager/providers/gcp.py
config_manager/utils/__init__.py
config_manager/utils/cache.py
config_manager/utils/logger.py
tbi_config_manager-0.0.8.dist-info/METADATA
tbi_config_manager-0.0.8.dist-info/WHEEL
tbi_config_manager-0.0.8.dist-info/licenses/LICENSE
tbi_config_manager-0.0.8.dist-info/RECORD
