Metadata-Version: 2.4
Name: tbi-config-manager
Version: 0.0.8
Summary: A flexible configuration management library for Python with multiple provider support (Environment, GCP Secret Manager, etc.) and easy extensibility.
Project-URL: Homepage, https://github.com/TaiwanBigdata/config-manager
Project-URL: Repository, https://github.com/TaiwanBigdata/config-manager.git
Author-email: Albert Liu <dreamerhyde@gmail.com>
License-Expression: MIT
License-File: LICENSE
Keywords: config,dotenv,env,environment,gcp,secret-manager,variables
Classifier: Development Status :: 4 - Beta
Classifier: Environment :: Console
Classifier: Intended Audience :: Developers
Classifier: License :: OSI Approved :: MIT License
Classifier: Operating System :: OS Independent
Classifier: Programming Language :: Python :: 3
Classifier: Programming Language :: Python :: 3.8
Classifier: Programming Language :: Python :: 3.9
Classifier: Programming Language :: Python :: 3.10
Classifier: Programming Language :: Python :: 3.11
Classifier: Programming Language :: Python :: 3.12
Classifier: Topic :: Security
Classifier: Topic :: Utilities
Requires-Python: >=3.8
Requires-Dist: google-cloud-secret-manager>=2.0.0
Requires-Dist: python-dotenv>=0.19.0
Requires-Dist: typing-extensions>=4.0.0
Provides-Extra: dev
Requires-Dist: black>=22.0.0; extra == 'dev'
Requires-Dist: flake8>=4.0.0; extra == 'dev'
Requires-Dist: isort>=5.0.0; extra == 'dev'
Requires-Dist: pytest-cov>=4.0.0; extra == 'dev'
Requires-Dist: pytest>=7.0.0; extra == 'dev'
